mermaid/__init__.py
mermaid/__main__.py
mermaid/configuration.py
mermaid/erdiagram/__init__.py
mermaid/erdiagram/entity.py
mermaid/erdiagram/link.py
mermaid/flowchart/__init__.py
mermaid/flowchart/link.py
mermaid/flowchart/node.py
mermaid/graph.py
mermaid/icon.py
mermaid/mindmap/__init__.py
mermaid/mindmap/level.py
mermaid/piechart.py
mermaid/reqdiagram/__init__.py
mermaid/reqdiagram/element.py
mermaid/reqdiagram/link.py
mermaid/reqdiagram/requirement.py
mermaid/sequence/__init__.py
mermaid/sequence/element.py
mermaid/sequence/link.py
mermaid/sequence/logic.py
mermaid/statediagram/__init__.py
mermaid/statediagram/base.py
mermaid/statediagram/state.py
mermaid/statediagram/transition.py
mermaid/style.py
mermaid/userjourney/__init__.py
mermaid/userjourney/actor.py
mermaid/userjourney/section.py
mermaid/userjourney/task.py
mermaid/utils.py
mermaid_py-0.7.0.dist-info/LICENSE
mermaid_py-0.7.0.dist-info/METADATA
mermaid_py-0.7.0.dist-info/WHEEL
mermaid_py-0.7.0.dist-info/RECORD
