Metadata-Version: 2.1
Name: mermaid-py
Version: 0.7.0
Summary: Python Interface for the Popular mermaid-js Library, Simplified for Diagram Creation.
Home-page: https://mermaidpy.vercel.app
License: MIT
Author: ouhammmourachid
Author-email: rachidouhammou21@gmail.com
Requires-Python: >=3.9,<4.0
Classifier: License :: OSI Approved :: MIT License
Classifier: Programming Language :: Python :: 3
Classifier: Programming Language :: Python :: 3.9
Classifier: Programming Language :: Python :: 3.10
Classifier: Programming Language :: Python :: 3.11
Classifier: Programming Language :: Python :: 3.12
Classifier: Programming Language :: Python :: 3.13
Requires-Dist: requests (>=2.31.0,<3.0.0)
Project-URL: Repository, https://github.com/ouhammmourachid/mermaid-py
